davidia/__init__.py
davidia/generate_openapi.py
davidia/main.py
davidia/plot.py
davidia/data/blobs-0.png
davidia/data/blobs-1.png
davidia/data/blobs-2.png
davidia/data/blobs-3.png
davidia/data/blobs-4.png
davidia/data/blobs-5.png
davidia/data/blobs-6.png
davidia/data/blobs-7.png
davidia/data/blobs-8.png
davidia/data/blobs-9.png
davidia/data/label-0.png
davidia/data/label-1.png
davidia/data/label-2.png
davidia/data/label-3.png
davidia/data/label-4.png
davidia/data/label-5.png
davidia/data/label-6.png
davidia/data/label-7.png
davidia/data/label-8.png
davidia/data/label-9.png
davidia/demos/__init__.py
davidia/demos/__main__.py
davidia/demos/benchmark.py
davidia/demos/simple.py
davidia/models/__init__.py
davidia/models/messages.py
davidia/models/parameters.py
davidia/models/selections.py
davidia/server/__init__.py
davidia/server/benchmarks.py
davidia/server/fastapi_utils.py
davidia/server/plotserver.py
davidia/server/processor.py
davidia/tests/__init__.py
davidia/tests/test_api.py
davidia/tests/test_plotserver.py
davidia/tests/test_selections.py
davidia-1.0.4.dist-info/METADATA
davidia-1.0.4.dist-info/WHEEL
davidia-1.0.4.dist-info/entry_points.txt
davidia-1.0.4.dist-info/top_level.txt
davidia-1.0.4.dist-info/RECORD
