Metadata-Version: 2.4
Name: davidia
Version: 1.0.4
Summary: Plot server with React frontend data visualiser
Home-page: https://github.com/DiamondLightSource/davidia
Author-email: dataanalysis@diamond.ac.uk
Requires-Python: >=3.10
Requires-Dist: before-after
Requires-Dist: fastapi
Requires-Dist: httpx
Requires-Dist: msgpack
Requires-Dist: pillow
Requires-Dist: pydantic-numpy
Requires-Dist: orjson
Requires-Dist: requests
Requires-Dist: uvicorn
Requires-Dist: websockets
Provides-Extra: test
Requires-Dist: pytest; extra == "test"
Requires-Dist: pytest-asyncio; extra == "test"
Provides-Extra: all
Requires-Dist: davidia-example-client; extra == "all"
Dynamic: author-email
Dynamic: description
Dynamic: description-content-type
Dynamic: home-page
Dynamic: provides-extra
Dynamic: requires-dist
Dynamic: requires-python
Dynamic: summary
